proclubsapi/__init__.py
proclubsapi/api.py
proclubs_api-0.1.dist-info/METADATA
proclubs_api-0.1.dist-info/WHEEL
proclubs_api-0.1.dist-info/top_level.txt
proclubs_api-0.1.dist-info/RECORD
