Metadata-Version: 2.1
Name: proclubs-api
Version: 0.1
Summary: An API do FIFA Pro Clubs
Home-page: UNKNOWN
Author: Marcelo Augusto
Author-email: marcelotk_15@hotmail.com
License: MIT
Platform: UNKNOWN
